jk_json/JsonParserRelaxed.py
jk_json/JsonParserStrict.py
jk_json/ObjectEncoder.py
jk_json/ParserBase.py
jk_json/ParserErrorException.py
jk_json/SourceCodeLocation.py
jk_json/Token.py
jk_json/TokenStream.py
jk_json/Tokenizer.md
jk_json/TokenizerBase.py
jk_json/TokenizerRelaxed.py
jk_json/TokenizerStrict.py
jk_json/__init__.py
jk_json/tools/__init__.py
jk_json/tools/tools.py
jk_json-0.2025.1.8.dist-info/entry_points.txt
jk_json-0.2025.1.8.dist-info/WHEEL
jk_json-0.2025.1.8.dist-info/METADATA
jk_json-0.2025.1.8.dist-info/RECORD
