Metadata-Version: 2.1
Name: jk_json
Version: 0.2025.1.8
Summary: This python module provides parser and validator for JSON files and data structures. The JSON parser is designed as a drop-in replacement for the built in python JSON parser as this parser here supports using comments in JSON files (which in some use cases is very a very handy feature).
Keywords: json,parsing,schema
Author-email: Jürgen Knauth <pubsrc@binary-overflow.de>
Maintainer-email: Jürgen Knauth <pubsrc@binary-overflow.de>
Requires-Python: >=3.8
Classifier: Development Status :: 3 - Alpha
Classifier: Programming Language :: Python :: 3
Requires-Dist: chardet
Requires-Dist: jk_typing
Requires-Dist: jk_prettyprintobj
Requires-Dist: jk_logging
Requires-Dist: jk_simpleexec
